babi_grammars.py
babi_grammars-0.0.65.data/data/share/babi/grammar_v1/source.arm.json
babi_grammars-0.0.65.data/data/share/babi/grammar_v1/source.asm.json
babi_grammars-0.0.65.data/data/share/babi/grammar_v1/source.batchfile.json
babi_grammars-0.0.65.data/data/share/babi/grammar_v1/source.bazel.json
babi_grammars-0.0.65.data/data/share/babi/grammar_v1/source.bazelrc.json
babi_grammars-0.0.65.data/data/share/babi/grammar_v1/source.c.json
babi_grammars-0.0.65.data/data/share/babi/grammar_v1/source.coffee.json
babi_grammars-0.0.65.data/data/share/babi/grammar_v1/source.cpp.embedded.macro.json
babi_grammars-0.0.65.data/data/share/babi/grammar_v1/source.cpp.json
babi_grammars-0.0.65.data/data/share/babi/grammar_v1/source.crystal.json
babi_grammars-0.0.65.data/data/share/babi/grammar_v1/source.cs.json
babi_grammars-0.0.65.data/data/share/babi/grammar_v1/source.css.json
babi_grammars-0.0.65.data/data/share/babi/grammar_v1/source.css.scss.json
babi_grammars-0.0.65.data/data/share/babi/grammar_v1/source.dart.json
babi_grammars-0.0.65.data/data/share/babi/grammar_v1/source.diff.json
babi_grammars-0.0.65.data/data/share/babi/grammar_v1/source.dockerfile.json
babi_grammars-0.0.65.data/data/share/babi/grammar_v1/source.elixir.json
babi_grammars-0.0.65.data/data/share/babi/grammar_v1/source.fsharp.json
babi_grammars-0.0.65.data/data/share/babi/grammar_v1/source.gleam.json
babi_grammars-0.0.65.data/data/share/babi/grammar_v1/source.go.json
babi_grammars-0.0.65.data/data/share/babi/grammar_v1/source.haskell.json
babi_grammars-0.0.65.data/data/share/babi/grammar_v1/source.hcl.json
babi_grammars-0.0.65.data/data/share/babi/grammar_v1/source.hcl.terraform.json
babi_grammars-0.0.65.data/data/share/babi/grammar_v1/source.ini.json
babi_grammars-0.0.65.data/data/share/babi/grammar_v1/source.jac.json
babi_grammars-0.0.65.data/data/share/babi/grammar_v1/source.java.json
babi_grammars-0.0.65.data/data/share/babi/grammar_v1/source.js.json
babi_grammars-0.0.65.dist-info/LICENSE
babi_grammars-0.0.65.dist-info/LICENSE_Dart-Code_Dart-Code
babi_grammars-0.0.65.dist-info/LICENSE_PowerShell_EditorSyntax
babi_grammars-0.0.65.dist-info/LICENSE_TingPing_language-meson
babi_grammars-0.0.65.dist-info/LICENSE_Xoronic_pest-Syntax-Highlighting-for-vscode
babi_grammars-0.0.65.dist-info/LICENSE_alefragnani_vscode-language-pascal
babi_grammars-0.0.65.dist-info/LICENSE_asottile_MagicPython
babi_grammars-0.0.65.dist-info/LICENSE_asottile_atom-language-rust
babi_grammars-0.0.65.dist-info/LICENSE_asottile_language-shellscript
babi_grammars-0.0.65.dist-info/LICENSE_asottile_language-xml
babi_grammars-0.0.65.dist-info/LICENSE_asottile_yaml.tmbundle
babi_grammars-0.0.65.dist-info/LICENSE_atom_language-css
babi_grammars-0.0.65.dist-info/LICENSE_atom_language-php
babi_grammars-0.0.65.dist-info/LICENSE_atom_language-sass
babi_grammars-0.0.65.dist-info/LICENSE_crystal-lang-tools_vscode-crystal-lang
babi_grammars-0.0.65.dist-info/LICENSE_dotnet_csharp-tmLanguage
babi_grammars-0.0.65.dist-info/LICENSE_elixir-editors_elixir-tmbundle
babi_grammars-0.0.65.dist-info/LICENSE_fadeevab_make.tmbundle
babi_grammars-0.0.65.dist-info/LICENSE_gleam-lang_vscode-gleam
babi_grammars-0.0.65.dist-info/LICENSE_grafana_vscode-jsonnet
babi_grammars-0.0.65.dist-info/LICENSE_hashicorp_syntax
babi_grammars-0.0.65.dist-info/LICENSE_ionide_ionide-fsgrammar
babi_grammars-0.0.65.dist-info/LICENSE_jaseci-labs_jaseci
babi_grammars-0.0.65.dist-info/LICENSE_jeff-hykin_better-c-syntax
babi_grammars-0.0.65.dist-info/LICENSE_jeff-hykin_better-cpp-syntax
babi_grammars-0.0.65.dist-info/LICENSE_jeff-hykin_better-go-syntax
babi_grammars-0.0.65.dist-info/LICENSE_jeff-hykin_better-objc-syntax
babi_grammars-0.0.65.dist-info/LICENSE_jeff-hykin_better-objcpp-syntax
babi_grammars-0.0.65.dist-info/LICENSE_lingua-pupuli_puppet-editor-syntax
babi_grammars-0.0.65.dist-info/LICENSE_microsoft_TypeScript-TmLanguage
babi_grammars-0.0.65.dist-info/LICENSE_microsoft_vscode
babi_grammars-0.0.65.dist-info/LICENSE_microsoft_vscode-JSON.tmLanguage
babi_grammars-0.0.65.dist-info/LICENSE_microsoft_vscode-markdown-tm-grammar
babi_grammars-0.0.65.dist-info/LICENSE_microsoft_vscode-mssql
babi_grammars-0.0.65.dist-info/LICENSE_mmims_language-batchfile
babi_grammars-0.0.65.dist-info/LICENSE_nishtahir_language-kotlin
babi_grammars-0.0.65.dist-info/LICENSE_pragmagic_vscode-nim
babi_grammars-0.0.65.dist-info/LICENSE_scala_vscode-scala-syntax
babi_grammars-0.0.65.dist-info/LICENSE_stackb_bazel-stack-vscode
babi_grammars-0.0.65.dist-info/LICENSE_textmate_diff.tmbundle
babi_grammars-0.0.65.dist-info/LICENSE_textmate_git.tmbundle
babi_grammars-0.0.65.dist-info/LICENSE_textmate_haskell.tmbundle
babi_grammars-0.0.65.dist-info/LICENSE_textmate_html.tmbundle
babi_grammars-0.0.65.dist-info/LICENSE_textmate_ini.tmbundle
babi_grammars-0.0.65.dist-info/LICENSE_textmate_lua.tmbundle
babi_grammars-0.0.65.dist-info/LICENSE_textmate_perl.tmbundle
babi_grammars-0.0.65.dist-info/LICENSE_textmate_r.tmbundle
babi_grammars-0.0.65.dist-info/LICENSE_textmate_ruby.tmbundle
babi_grammars-0.0.65.dist-info/LICENSE_textmate_swift.tmbundle
babi_grammars-0.0.65.dist-info/LICENSE_textmate_toml.tmbundle
babi_grammars-0.0.65.dist-info/LICENSE_trond-snekvik_vscode-rst
babi_grammars-0.0.65.dist-info/LICENSE_ziglang_vscode-zig
babi_grammars-0.0.65.dist-info/METADATA
babi_grammars-0.0.65.dist-info/WHEEL
babi_grammars-0.0.65.dist-info/top_level.txt
babi_grammars-0.0.65.dist-info/RECORD
