Metadata-Version: 2.1
Name: babi_grammars
Version: 0.0.65
Summary: grammars for babi
Home-page: https://github.com/asottile/babi-grammars
Author: Anthony Sottile
Author-email: asottile@umich.edu
License: MIT
Classifier: Programming Language :: Python :: 3
Classifier: Programming Language :: Python :: 3 :: Only
Classifier: Programming Language :: Python :: Implementation :: CPython
Classifier: Programming Language :: Python :: Implementation :: PyPy
Requires-Python: >=3.10
License-File: LICENSE
License-File: licenses/LICENSE_Dart-Code_Dart-Code
License-File: licenses/LICENSE_PowerShell_EditorSyntax
License-File: licenses/LICENSE_TingPing_language-meson
License-File: licenses/LICENSE_Xoronic_pest-Syntax-Highlighting-for-vscode
License-File: licenses/LICENSE_alefragnani_vscode-language-pascal
License-File: licenses/LICENSE_asottile_MagicPython
License-File: licenses/LICENSE_asottile_atom-language-rust
License-File: licenses/LICENSE_asottile_language-shellscript
License-File: licenses/LICENSE_asottile_language-xml
License-File: licenses/LICENSE_asottile_yaml.tmbundle
License-File: licenses/LICENSE_atom_language-css
License-File: licenses/LICENSE_atom_language-php
License-File: licenses/LICENSE_atom_language-sass
License-File: licenses/LICENSE_crystal-lang-tools_vscode-crystal-lang
License-File: licenses/LICENSE_dotnet_csharp-tmLanguage
License-File: licenses/LICENSE_elixir-editors_elixir-tmbundle
License-File: licenses/LICENSE_fadeevab_make.tmbundle
License-File: licenses/LICENSE_gleam-lang_vscode-gleam
License-File: licenses/LICENSE_grafana_vscode-jsonnet
License-File: licenses/LICENSE_hashicorp_syntax
License-File: licenses/LICENSE_ionide_ionide-fsgrammar
License-File: licenses/LICENSE_jaseci-labs_jaseci
License-File: licenses/LICENSE_jeff-hykin_better-c-syntax
License-File: licenses/LICENSE_jeff-hykin_better-cpp-syntax
License-File: licenses/LICENSE_jeff-hykin_better-go-syntax
License-File: licenses/LICENSE_jeff-hykin_better-objc-syntax
License-File: licenses/LICENSE_jeff-hykin_better-objcpp-syntax
License-File: licenses/LICENSE_lingua-pupuli_puppet-editor-syntax
License-File: licenses/LICENSE_microsoft_TypeScript-TmLanguage
License-File: licenses/LICENSE_microsoft_vscode
License-File: licenses/LICENSE_microsoft_vscode-JSON.tmLanguage
License-File: licenses/LICENSE_microsoft_vscode-markdown-tm-grammar
License-File: licenses/LICENSE_microsoft_vscode-mssql
License-File: licenses/LICENSE_mmims_language-batchfile
License-File: licenses/LICENSE_nishtahir_language-kotlin
License-File: licenses/LICENSE_pragmagic_vscode-nim
License-File: licenses/LICENSE_scala_vscode-scala-syntax
License-File: licenses/LICENSE_stackb_bazel-stack-vscode
License-File: licenses/LICENSE_textmate_diff.tmbundle
License-File: licenses/LICENSE_textmate_git.tmbundle
License-File: licenses/LICENSE_textmate_haskell.tmbundle
License-File: licenses/LICENSE_textmate_html.tmbundle
License-File: licenses/LICENSE_textmate_ini.tmbundle
License-File: licenses/LICENSE_textmate_lua.tmbundle
License-File: licenses/LICENSE_textmate_perl.tmbundle
License-File: licenses/LICENSE_textmate_r.tmbundle
License-File: licenses/LICENSE_textmate_ruby.tmbundle
License-File: licenses/LICENSE_textmate_swift.tmbundle
License-File: licenses/LICENSE_textmate_toml.tmbundle
License-File: licenses/LICENSE_trond-snekvik_vscode-rst
License-File: licenses/LICENSE_ziglang_vscode-zig
